vision_models_evaluation/__init__.py
vision_models_evaluation/_modidx.py
vision_models_evaluation/core.py
vision_models_evaluation-0.0.5.dist-info/LICENSE
vision_models_evaluation-0.0.5.dist-info/METADATA
vision_models_evaluation-0.0.5.dist-info/WHEEL
vision_models_evaluation-0.0.5.dist-info/entry_points.txt
vision_models_evaluation-0.0.5.dist-info/top_level.txt
vision_models_evaluation-0.0.5.dist-info/RECORD
