Metadata-Version: 2.1
Name: vision-models-evaluation
Version: 0.0.5
Summary: A library to test fastai learners using some evaluation techniques.
Home-page: https://github.com/ruescog/vision_models_evaluation
Author: ruescog
Author-email: ruescog@unirioja.es
License: Apache Software License 2.0
Keywords: nbdev jupyter notebook python
Platform: UNKNOWN
Classifier: Development Status :: 4 - Beta
Classifier: Intended Audience :: Developers
Classifier: Natural Language :: English
Classifier: Programming Language :: Python :: 3.7
Classifier: Programming Language :: Python :: 3.8
Classifier: Programming Language :: Python :: 3.9
Classifier: Programming Language :: Python :: 3.10
Classifier: License :: OSI Approved :: Apache Software License
Requires-Python: >=3.7
Requires-Dist: fastai
Requires-Dist: fastcore
Requires-Dist: pandas
Requires-Dist: scikit-learn
Provides-Extra: dev
